{"id":"39243558","premium":false,"billing_type":{"id":"standard","name":"Стандарт"},"relations":[],"name":"Системный аналитик","insider_interview":null,"response_letter_required":false,"area":{"id":"112","name":"Ярославль","url":"https://api.hh.ru/areas/112?host=hh.ru"},"salary":{"from":120000,"to":160000,"currency":"RUR","gross":true},"type":{"id":"open","name":"Открытая"},"address":null,"allow_messages":true,"site":{"id":"hh","name":"hh.ru"},"experience":{"id":"between3And6","name":"От 3 до 6 лет"},"schedule":{"id":"fullDay","name":"Полный день"},"employment":{"id":"full","name":"Полная занятость"},"department":null,"contacts":null,"description":"<p><strong><em>АО «НПО Ангстрем» — это молодая независимая компания, стремительно развивающаяся на отечественном рынке средств радиосвязи специального назначения. Мы производим уникальные решения, аналогов которым до сих пор нет в мире. Мы знаем ценность этих решений. Мы верим в себя, свою страну и в то, что от каждого из нас зависит, в каком обществе мы будем жить.</em></strong></p> <p><strong>Обязанности:</strong></p> <ul> <li>Анализ бизнес-требований;</li> <li>Участие в разработке макетов пользовательского интерфейса;</li> <li>Разработка требований к новым методам сервисов, проектирование поведения новых методов;</li> <li>Составление сценариев взаимодействия frontend-продукта с сервисами;</li> <li>Проектирование поведения разрабатываемого frontend-продукта;</li> <li>Участие в создании плана тестирования продукта;</li> <li>Контроль полноты плана тестирования;</li> <li>Участие в тестировании продукта, проверка основных сценариев использования продукта;</li> <li>Подготовка сценариев показов и исходных данных для показов;</li> </ul> <strong>Требования:</strong> <ul> <li>Умение проектировать схемы баз данных;</li> <li>Умение проектировать веб-сервисы;</li> <li>Умение проектировать сценарии взаимодействия фронтэнд-продукта с сервисами;</li> <li>Умение проектировать сценарии взаимодействия элементов пользовательского интерфейса с пользователем и между собой;</li> <li>От 3 лет, подтверждённые проекты в качестве Senior разработчика Java</li> </ul> <p><strong>Будет плюсом:</strong></p> <ul> <li>Знание различных типов диаграмм UML;</li> <li>Понимание принципов работы WebAPI, понимание HTTP-кодов;</li> <li>Опыт разработки макетов пользовательского интерфейса или опыт разработки пользовательского интерфейса;</li> <li>Навыки организации и управления работой команды (технические писатели, тестировщики, разработчики);</li> <li>Знание операционных систем семейства UNIX.</li> </ul> <strong>Условия:</strong> <ul> <li>Соблюдение ТК РФ по всем вопросам, касающимся работы с персоналом</li> <li>Конкурентоспособная, полностью белая заработная плата</li> <li>Развивающаяся корпоративная жизнь</li> <li>Возможность повышения квалификации</li> <li>Интересные проекты, амбициозные задачи</li> <li>Сплоченная команда профессионалов</li> <li>Участие в проектах национального масштаба</li> </ul>","branded_description":null,"vacancy_constructor_template":null,"key_skills":[{"name":"UML"},{"name":"Java"},{"name":"WebAPI"},{"name":"Unix"}],"accept_handicapped":false,"accept_kids":false,"archived":false,"response_url":null,"specializations":[{"id":"5.27","name":"Аналитик","profarea_id":"5","profarea_name":"Банки, инвестиции, лизинг"},{"id":"1.274","name":"Системы автоматизированного проектирования","profarea_id":"1","profarea_name":"Информационные технологии, интернет, телеком"},{"id":"1.25","name":"Аналитик","profarea_id":"1","profarea_name":"Информационные технологии, интернет, телеком"},{"id":"18.245","name":"Радиоэлектронная промышленность","profarea_id":"18","profarea_name":"Производство, сельское хозяйство"}],"code":null,"hidden":false,"quick_responses_allowed":false,"driver_license_types":[],"accept_incomplete_resumes":false,"employer":{"id":"1395186","name":"НПО АНГСТРЕМ","url":"https://api.hh.ru/employers/1395186?host=hh.ru","alternate_url":"https://hh.ru/employer/1395186","logo_urls":{"original":"https://hhcdn.ru/employer-logo-original/322181.png","90":"https://hhcdn.ru/employer-logo/1731090.png","240":"https://hhcdn.ru/employer-logo/1731091.png"},"vacancies_url":"https://api.hh.ru/vacancies?employer_id=1395186&host=hh.ru","trusted":true},"published_at":"2021-03-15T09:43:54+0300","created_at":"2021-03-15T09:43:54+0300","negotiations_url":null,"suitable_resumes_url":null,"apply_alternate_url":"https://hh.ru/applicant/vacancy_response?vacancyId=39243558","has_test":false,"test":null,"alternate_url":"https://hh.ru/vacancy/39243558","working_days":[],"working_time_intervals":[],"working_time_modes":[],"accept_temporary":false}